MANIFEST.in
Readme.md
setup.py
i3theme/__init__.py
i3theme/i3theme.py
i3theme.egg-info/PKG-INFO
i3theme.egg-info/SOURCES.txt
i3theme.egg-info/dependency_links.txt
i3theme.egg-info/entry_points.txt
i3theme.egg-info/requires.txt
i3theme.egg-info/top_level.txt
i3theme/themes/archlinux
i3theme/themes/base16-tomorrow
i3theme/themes/debian
i3theme/themes/deep-purple
i3theme/themes/default
i3theme/themes/flat-gray
i3theme/themes/gruvbox
i3theme/themes/icelines
i3theme/themes/lime
i3theme/themes/okraits
i3theme/themes/purple
i3theme/themes/seti
i3theme/themes/slate
i3theme/themes/solarized
i3theme/themes/tomorrow-night-80s
i3theme/themes/ubuntu
i3theme/utils/__init__.py
i3theme/utils/argparser.py
i3theme/utils/filebridge.py
i3theme/utils/main.py
i3theme/utils/themeparser.py