Metadata-Version: 1.0
Name: i3theme
Version: 1.4
Summary: Simple utility to apply Yaml formated theme to i3wm.
Home-page: UNKNOWN
Author: manzerbredes
Author-email: pip-account@loicguegan.fr
License: GPL
Keywords: i3wm theme
Platform: UNKNOWN
